np/__init__.py
np/core.py
np/icons.py
np/main.py
np/media.py
np/utils.py
now_playing_gui-0.2.0.dist-info/METADATA
now_playing_gui-0.2.0.dist-info/WHEEL
now_playing_gui-0.2.0.dist-info/entry_points.txt
now_playing_gui-0.2.0.dist-info/top_level.txt
now_playing_gui-0.2.0.dist-info/RECORD
