Metadata-Version: 2.4
Name: now-playing-gui
Version: 0.2.0
Project-URL: repository, https://github.com/raffleberry/now-playing
Requires-Python: >=3.13
Requires-Dist: pyside6>=6.10.0
Requires-Dist: winrt-windows-foundation>=3.2.1
Requires-Dist: winrt-windows-foundation-collections>=3.2.1
Requires-Dist: winrt-windows-media>=3.2.1
Requires-Dist: winrt-windows-media-control>=3.2.1
Requires-Dist: winrt-windows-storage-streams>=3.2.1
Requires-Dist: winrt-windows-system>=3.2.1
